Workbook

Sheet 1. Parametros y Tarifas
A1: CONFIGURACIÓN DE PARÁMETROS - IMPORTACIONES PERÚ
A3: 1. IMPUESTOS ADUANEROS (SUNAT)
A4: Tasa IGV (Impuesto General a las Ventas) | B4: 0.16 | C4: Crédito fiscal (tasa estándar 16%)
A5: Tasa IPM (Impuesto Promoción Municipal) | B5: 0.02 | C5: Crédito fiscal (tasa estándar 2%)
A6: IGV + IPM Total (Base para importaciones) | B6: =B4+B5 | C6: Suma total de impuestos a las ventas (18%)
A7: Percepción IGV (Primera Importación) | B7: 0.1 | C7: Aplicable en la primera DUA/DAM del importador
A8: Percepción IGV (Importador Frecuente) | B8: 0.035 | C8: Aplicable para importaciones habituales (defecto)
A9: Percepción IGV (Bienes Usados) | B9: 0.05 | C9: Aplicable para la importación de mercancías usadas
A10: Tipo de Cambio Oficial (S/ por USD) | B10: 3.78 | C10: Tasa de cambio comercial promedio (editable)
A12: 2. GASTOS LOCALES DE DESPACHO (USD)
A13: Comisión Agente de Aduanas (%) | B13: 0.005 | C13: Porcentaje sobre el valor CIF de la importación
A14: Tarifa Mínima Agente de Aduanas (USD) | B14: 200 | C14: Cobro mínimo si la comisión por % es menor
A15: Gastos Portuarios / Desconsolidación | B15: 180 | C15: Gastos de descarga y desconsolidación de contenedor
A16: Almacenaje Aduanero (Depósito Temporal) | B16: 150 | C16: Almacén temporal autorizado de aduanas
A17: Flete Local (Transporte Terrestre Interno) | B17: 220 | C17: Traslado de aduana/puerto al almacén del cliente
A18: Gastos Bancarios (SWIFT / Transferencias) | B18: 45 | C18: Gastos de transferencia internacional al proveedor
A19: Gastos Administrativos / Logísticos Varios | B19: 80 | C19: Gastos operativos, copias, mensajería, etc.
A20: Total Gastos Locales Fijos | B20: =SUM(B15:B19) | C20: Suma de gastos portuarios, flete interno, almacén y varios
A22: 3. FLETES Y SEGUROS DE REFERENCIA (USD)
A23: Flete Marítimo por CBM (LCL) | B23: 110 | C23: Costo promedio de flete por metro cúbico
A24: Flete Marítimo por Tonelada LCL | B24: 130 | C24: Costo promedio de flete por 1000 kg
A25: Flete Aéreo por Kilogramo | B25: 4.8 | C25: Tarifa de flete aéreo internacional por kg
A26: Seguro Estimado de Aduana (%) | B26: 0.015 | C26: 1.5% del valor FOB + Flete (fórmula de tabla SUNAT)

Sheet 2. Calculadora Individual
A1: CALCULADORA DE IMPORTACIÓN INDIVIDUAL
A3: DATOS DE LA MERCANCÍA Y EMBARQUE
A4: Nombre del Producto | B4: Audífonos Bluetooth Premium | C4: Identificador comercial
A5: Precio FOB Total (USD) | B5: 3500 | C5: Valor de la mercancía en puerto de origen
A6: Cantidad de Unidades (Uds) | B6: 500 | C6: Número de productos a importar
A7: Peso Neto Total (kg) | B7: 85 | C7: Peso neto total de la carga
A8: Volumen Total (CBM) | B8: 0.65 | C8: Volumen en metros cúbicos
A9: Tipo de Transporte | B9: Marítimo | C9: Seleccionar 'Marítimo' o 'Aéreo'
A10: Origen de la Mercancía | B10: China | C10: Seleccionar origen para recargos de flete
A11: Tasa Ad-Valorem / Arancel (%) | B11: 0.06 | C11: Tasa SUNAT según partida (0%, 4%, 6%, 11%)
A12: Percepción IGV Aplicable | B12: Importador Frecuente (3.5%) | C12: Tasa de percepción de IGV
A13: Margen de Ganancia Deseado (%) | B13: 0.35 | C13: Margen de ganancia bruto objetivo
A15: DESGLOSE DE GASTOS E IMPUESTOS DE IMPORTACIÓN
A16: Flete Internacional | B16: =IF(B9="Marítimo", MAX(B8*'1. Parametros y Tarifas'!$B$23, (B7/1000)*'1. Parametros y Tarifas'!$B$24), B7*'1. Parametros y Tarifas'!$B$25) * IF(B10="Europa", 1.2, IF(B10="EEUU", 1.1, 1.0)) | C16: Prorrateado por peso o volumen más recargo de origen
A17: Seguro de Aduana (Estimado/Real) | B17: =(B5+B16)*'1. Parametros y Tarifas'!$B$26 | C17: Costo de póliza o seguro estimado SUNAT
A18: Valor CIF (Costo + Flete + Seguro) | B18: =B5+B16+B17 | C18: Valor base imponible de aduana (CIF)
A19: Derechos Arancelarios (Ad-Valorem) | B19: =B18*B11 | C19: Arancel cobrado en aduana peruana
A20: Impuesto General a las Ventas (IGV 16%) | B20: =(B18+B19)*'1. Parametros y Tarifas'!$B$4 | C20: Impuesto local IGV (Crédito Fiscal)
A21: Impuesto Promoción Municipal (IPM 2%) | B21: =(B18+B19)*'1. Parametros y Tarifas'!$B$5 | C21: Impuesto local IPM (Crédito Fiscal)
A22: Gastos Operativos Locales (Despacho) | B22: =MAX('1. Parametros y Tarifas'!$B$14, B18*'1. Parametros y Tarifas'!$B$13) + '1. Parametros y Tarifas'!$B$20 | C22: Agente aduanas, puerto, almacén y transporte local
A23: Percepción IGV (SUNAT) | B23: =(B18+B19+B20+B21)*IF(B12="Primera Importación (10%)", '1. Parametros y Tarifas'!$B$7, IF(B12="Bienes Usados (5%)", '1. Parametros y Tarifas'!$B$9, IF(B12="No Aplicable (0%)", 0, '1. Parametros y Tarifas'!$B$8))) | C23: Pago por adelantado del IGV local (Crédito Fiscal)
A25: ANÁLISIS DE COSTOS REALES Y PRECIOS DE VENTA
A26: Costo Total en Almacén (Real Cost) | B26: =B18+B19+B22 | C26: Suma de CIF + Arancel + Gastos Locales (No incluye IGV)
A27: Costo Unitario en Almacén (USD) | B27: =B26/B6 | C27: Costo unitario real puesto en almacén (excl. IGV)
A28: Costo Unitario en Almacén (PEN) | B28: =B27*'1. Parametros y Tarifas'!$B$10 | C28: Costo unitario real convertido a Soles
A29: Impuestos Recuperables (Crédito Fiscal) | B29: =B20+B21+B23 | C29: IGV + IPM + Percepción que se recuperan en ventas locales
A30: Desembolso de Caja Total (Caja) | B30: =B26+B29 | C30: Dinero total necesario para desaduanar y almacenar
A31: Precio Venta Sugerido (USD - Sin IGV) | B31: =B27/(1-B13) | C31: Precio unitario para obtener el margen neto deseado
A32: Precio Venta Sugerido (PEN - Sin IGV) | B32: =B31*'1. Parametros y Tarifas'!$B$10 | C32: Precio unitario en Soles sin IGV local
A33: Precio Venta Sugerido Público (PEN - Con IGV) | B33: =B32*1.18 | C33: Precio final al público con IGV incluido (18%)
A34: Utilidad Neta Total Estimada (USD) | B34: =(B31-B27)*B6 | C34: Ganancia bruta total proyectada (excluyendo IGV)

Sheet 3. Prorrateo Multi-Producto
A1: CUADRO DE PRORRATEO Y DISTRIBUCIÓN DE COSTOS DE IMPORTACIÓN
A3: GASTOS GENERALES DEL EMBARQUE
A4: Flete Internacional Facturado (USD) | B4: 1850
A5: Seguro Internacional Facturado (USD) | B5: 125
A6: Gastos Locales de Despacho (USD) | B6: 890
A7: Criterio de Prorrateo del Flete | B7: Volumen
A8: Tasa de Percepción IGV (%) | B8: 0.035
A9: Tipo de Cambio Oficial (S/.) | B9: ='1. Parametros y Tarifas'!B10
A11: Item | B11: SKU / Código | C11: Descripción | D11: Cantidad (Uds) | E11: FOB Unit (USD) | F11: Peso Unit (kg) | G11: Vol Unit (CBM) | H11: Arancel % | I11: FOB Total (USD) | J11: Peso Total (kg) | K11: Vol Total (CBM) | L11: Flete Asig (USD) | M11: Seguro Asig (USD) | N11: CIF Total (USD) | O11: CIF Unit (USD) | P11: Ad-Valorem (USD) | Q11: Gastos Loc. (USD) | R11: Cost Almacén (USD) | S11: Cost Unit Alm (USD) | T11: Margen % | U11: P. Venta USD (sin IGV) | V11: P. Venta PEN (sin IGV) | W11: Util Total (USD) | X11: IGV+IPM Aduana | Y11: Percepción (USD)
A12: 1 | B12: SKU-9081 | C12: Smartphones Android 12 | D12: 200 | E12: 150 | F12: 0.25 | G12: 0.002 | H12: 0 | I12: =D12*E12 | J12: =D12*F12 | K12: =D12*G12 | L12: =IFERROR(IF($B$7="Peso", J12/SUM($J$12:$J$26)*$B$4, IF($B$7="Volumen", K12/SUM($K$12:$K$26)*$B$4, I12/SUM($I$12:$I$26)*$B$4)), 0) | M12: =IFERROR(I12/SUM($I$12:$I$26)*$B$5, 0) | N12: =I12+L12+M12 | O12: =IFERROR(N12/D12, 0) | P12: =N12*H12 | Q12: =IFERROR(I12/SUM($I$12:$I$26)*$B$6, 0) | R12: =N12+P12+Q12 | S12: =IFERROR(R12/D12, 0) | T12: 0.35 | U12: =IFERROR(S12/(1-T12), 0) | V12: =U12*$B$9 | W12: =(U12-S12)*D12 | X12: =(N12+P12)*'1. Parametros y Tarifas'!$B$6 | Y12: =(N12+P12+X12)*$B$8
A13: 2 | B13: SKU-4402 | C13: Fundas de Silicona TPU | D13: 1500 | E13: 1.2 | F13: 0.04 | G13: 0.0005 | H13: 0.06 | I13: =D13*E13 | J13: =D13*F13 | K13: =D13*G13 | L13: =IFERROR(IF($B$7="Peso", J13/SUM($J$12:$J$26)*$B$4, IF($B$7="Volumen", K13/SUM($K$12:$K$26)*$B$4, I13/SUM($I$12:$I$26)*$B$4)), 0) | M13: =IFERROR(I13/SUM($I$12:$I$26)*$B$5, 0) | N13: =I13+L13+M13 | O13: =IFERROR(N13/D13, 0) | P13: =N13*H13 | Q13: =IFERROR(I13/SUM($I$12:$I$26)*$B$6, 0) | R13: =N13+P13+Q13 | S13: =IFERROR(R13/D13, 0) | T13: 0.4 | U13: =IFERROR(S13/(1-T13), 0) | V13: =U13*$B$9 | W13: =(U13-S13)*D13 | X13: =(N13+P13)*'1. Parametros y Tarifas'!$B$6 | Y13: =(N13+P13+X13)*$B$8
A14: 3 | B14: SKU-5211 | C14: Cargadores Inalámbricos 15W | D14: 800 | E14: 8.5 | F14: 0.12 | G14: 0.001 | H14: 0.06 | I14: =D14*E14 | J14: =D14*F14 | K14: =D14*G14 | L14: =IFERROR(IF($B$7="Peso", J14/SUM($J$12:$J$26)*$B$4, IF($B$7="Volumen", K14/SUM($K$12:$K$26)*$B$4, I14/SUM($I$12:$I$26)*$B$4)), 0) | M14: =IFERROR(I14/SUM($I$12:$I$26)*$B$5, 0) | N14: =I14+L14+M14 | O14: =IFERROR(N14/D14, 0) | P14: =N14*H14 | Q14: =IFERROR(I14/SUM($I$12:$I$26)*$B$6, 0) | R14: =N14+P14+Q14 | S14: =IFERROR(R14/D14, 0) | T14: 0.35 | U14: =IFERROR(S14/(1-T14), 0) | V14: =U14*$B$9 | W14: =(U14-S14)*D14 | X14: =(N14+P14)*'1. Parametros y Tarifas'!$B$6 | Y14: =(N14+P14+X14)*$B$8
I15: =D15*E15 | J15: =D15*F15 | K15: =D15*G15 | L15: =IFERROR(IF($B$7="Peso", J15/SUM($J$12:$J$26)*$B$4, IF($B$7="Volumen", K15/SUM($K$12:$K$26)*$B$4, I15/SUM($I$12:$I$26)*$B$4)), 0) | M15: =IFERROR(I15/SUM($I$12:$I$26)*$B$5, 0) | N15: =I15+L15+M15 | O15: =IFERROR(N15/D15, 0) | P15: =N15*H15 | Q15: =IFERROR(I15/SUM($I$12:$I$26)*$B$6, 0) | R15: =N15+P15+Q15 | S15: =IFERROR(R15/D15, 0) | U15: =IFERROR(S15/(1-T15), 0) | V15: =U15*$B$9 | W15: =(U15-S15)*D15 | X15: =(N15+P15)*'1. Parametros y Tarifas'!$B$6 | Y15: =(N15+P15+X15)*$B$8
I16: =D16*E16 | J16: =D16*F16 | K16: =D16*G16 | L16: =IFERROR(IF($B$7="Peso", J16/SUM($J$12:$J$26)*$B$4, IF($B$7="Volumen", K16/SUM($K$12:$K$26)*$B$4, I16/SUM($I$12:$I$26)*$B$4)), 0) | M16: =IFERROR(I16/SUM($I$12:$I$26)*$B$5, 0) | N16: =I16+L16+M16 | O16: =IFERROR(N16/D16, 0) | P16: =N16*H16 | Q16: =IFERROR(I16/SUM($I$12:$I$26)*$B$6, 0) | R16: =N16+P16+Q16 | S16: =IFERROR(R16/D16, 0) | U16: =IFERROR(S16/(1-T16), 0) | V16: =U16*$B$9 | W16: =(U16-S16)*D16 | X16: =(N16+P16)*'1. Parametros y Tarifas'!$B$6 | Y16: =(N16+P16+X16)*$B$8
I17: =D17*E17 | J17: =D17*F17 | K17: =D17*G17 | L17: =IFERROR(IF($B$7="Peso", J17/SUM($J$12:$J$26)*$B$4, IF($B$7="Volumen", K17/SUM($K$12:$K$26)*$B$4, I17/SUM($I$12:$I$26)*$B$4)), 0) | M17: =IFERROR(I17/SUM($I$12:$I$26)*$B$5, 0) | N17: =I17+L17+M17 | O17: =IFERROR(N17/D17, 0) | P17: =N17*H17 | Q17: =IFERROR(I17/SUM($I$12:$I$26)*$B$6, 0) | R17: =N17+P17+Q17 | S17: =IFERROR(R17/D17, 0) | U17: =IFERROR(S17/(1-T17), 0) | V17: =U17*$B$9 | W17: =(U17-S17)*D17 | X17: =(N17+P17)*'1. Parametros y Tarifas'!$B$6 | Y17: =(N17+P17+X17)*$B$8
I18: =D18*E18 | J18: =D18*F18 | K18: =D18*G18 | L18: =IFERROR(IF($B$7="Peso", J18/SUM($J$12:$J$26)*$B$4, IF($B$7="Volumen", K18/SUM($K$12:$K$26)*$B$4, I18/SUM($I$12:$I$26)*$B$4)), 0) | M18: =IFERROR(I18/SUM($I$12:$I$26)*$B$5, 0) | N18: =I18+L18+M18 | O18: =IFERROR(N18/D18, 0) | P18: =N18*H18 | Q18: =IFERROR(I18/SUM($I$12:$I$26)*$B$6, 0) | R18: =N18+P18+Q18 | S18: =IFERROR(R18/D18, 0) | U18: =IFERROR(S18/(1-T18), 0) | V18: =U18*$B$9 | W18: =(U18-S18)*D18 | X18: =(N18+P18)*'1. Parametros y Tarifas'!$B$6 | Y18: =(N18+P18+X18)*$B$8
I19: =D19*E19 | J19: =D19*F19 | K19: =D19*G19 | L19: =IFERROR(IF($B$7="Peso", J19/SUM($J$12:$J$26)*$B$4, IF($B$7="Volumen", K19/SUM($K$12:$K$26)*$B$4, I19/SUM($I$12:$I$26)*$B$4)), 0) | M19: =IFERROR(I19/SUM($I$12:$I$26)*$B$5, 0) | N19: =I19+L19+M19 | O19: =IFERROR(N19/D19, 0) | P19: =N19*H19 | Q19: =IFERROR(I19/SUM($I$12:$I$26)*$B$6, 0) | R19: =N19+P19+Q19 | S19: =IFERROR(R19/D19, 0) | U19: =IFERROR(S19/(1-T19), 0) | V19: =U19*$B$9 | W19: =(U19-S19)*D19 | X19: =(N19+P19)*'1. Parametros y Tarifas'!$B$6 | Y19: =(N19+P19+X19)*$B$8
I20: =D20*E20 | J20: =D20*F20 | K20: =D20*G20 | L20: =IFERROR(IF($B$7="Peso", J20/SUM($J$12:$J$26)*$B$4, IF($B$7="Volumen", K20/SUM($K$12:$K$26)*$B$4, I20/SUM($I$12:$I$26)*$B$4)), 0) | M20: =IFERROR(I20/SUM($I$12:$I$26)*$B$5, 0) | N20: =I20+L20+M20 | O20: =IFERROR(N20/D20, 0) | P20: =N20*H20 | Q20: =IFERROR(I20/SUM($I$12:$I$26)*$B$6, 0) | R20: =N20+P20+Q20 | S20: =IFERROR(R20/D20, 0) | U20: =IFERROR(S20/(1-T20), 0) | V20: =U20*$B$9 | W20: =(U20-S20)*D20 | X20: =(N20+P20)*'1. Parametros y Tarifas'!$B$6 | Y20: =(N20+P20+X20)*$B$8
I21: =D21*E21 | J21: =D21*F21 | K21: =D21*G21 | L21: =IFERROR(IF($B$7="Peso", J21/SUM($J$12:$J$26)*$B$4, IF($B$7="Volumen", K21/SUM($K$12:$K$26)*$B$4, I21/SUM($I$12:$I$26)*$B$4)), 0) | M21: =IFERROR(I21/SUM($I$12:$I$26)*$B$5, 0) | N21: =I21+L21+M21 | O21: =IFERROR(N21/D21, 0) | P21: =N21*H21 | Q21: =IFERROR(I21/SUM($I$12:$I$26)*$B$6, 0) | R21: =N21+P21+Q21 | S21: =IFERROR(R21/D21, 0) | U21: =IFERROR(S21/(1-T21), 0) | V21: =U21*$B$9 | W21: =(U21-S21)*D21 | X21: =(N21+P21)*'1. Parametros y Tarifas'!$B$6 | Y21: =(N21+P21+X21)*$B$8
I22: =D22*E22 | J22: =D22*F22 | K22: =D22*G22 | L22: =IFERROR(IF($B$7="Peso", J22/SUM($J$12:$J$26)*$B$4, IF($B$7="Volumen", K22/SUM($K$12:$K$26)*$B$4, I22/SUM($I$12:$I$26)*$B$4)), 0) | M22: =IFERROR(I22/SUM($I$12:$I$26)*$B$5, 0) | N22: =I22+L22+M22 | O22: =IFERROR(N22/D22, 0) | P22: =N22*H22 | Q22: =IFERROR(I22/SUM($I$12:$I$26)*$B$6, 0) | R22: =N22+P22+Q22 | S22: =IFERROR(R22/D22, 0) | U22: =IFERROR(S22/(1-T22), 0) | V22: =U22*$B$9 | W22: =(U22-S22)*D22 | X22: =(N22+P22)*'1. Parametros y Tarifas'!$B$6 | Y22: =(N22+P22+X22)*$B$8
I23: =D23*E23 | J23: =D23*F23 | K23: =D23*G23 | L23: =IFERROR(IF($B$7="Peso", J23/SUM($J$12:$J$26)*$B$4, IF($B$7="Volumen", K23/SUM($K$12:$K$26)*$B$4, I23/SUM($I$12:$I$26)*$B$4)), 0) | M23: =IFERROR(I23/SUM($I$12:$I$26)*$B$5, 0) | N23: =I23+L23+M23 | O23: =IFERROR(N23/D23, 0) | P23: =N23*H23 | Q23: =IFERROR(I23/SUM($I$12:$I$26)*$B$6, 0) | R23: =N23+P23+Q23 | S23: =IFERROR(R23/D23, 0) | U23: =IFERROR(S23/(1-T23), 0) | V23: =U23*$B$9 | W23: =(U23-S23)*D23 | X23: =(N23+P23)*'1. Parametros y Tarifas'!$B$6 | Y23: =(N23+P23+X23)*$B$8
I24: =D24*E24 | J24: =D24*F24 | K24: =D24*G24 | L24: =IFERROR(IF($B$7="Peso", J24/SUM($J$12:$J$26)*$B$4, IF($B$7="Volumen", K24/SUM($K$12:$K$26)*$B$4, I24/SUM($I$12:$I$26)*$B$4)), 0) | M24: =IFERROR(I24/SUM($I$12:$I$26)*$B$5, 0) | N24: =I24+L24+M24 | O24: =IFERROR(N24/D24, 0) | P24: =N24*H24 | Q24: =IFERROR(I24/SUM($I$12:$I$26)*$B$6, 0) | R24: =N24+P24+Q24 | S24: =IFERROR(R24/D24, 0) | U24: =IFERROR(S24/(1-T24), 0) | V24: =U24*$B$9 | W24: =(U24-S24)*D24 | X24: =(N24+P24)*'1. Parametros y Tarifas'!$B$6 | Y24: =(N24+P24+X24)*$B$8
I25: =D25*E25 | J25: =D25*F25 | K25: =D25*G25 | L25: =IFERROR(IF($B$7="Peso", J25/SUM($J$12:$J$26)*$B$4, IF($B$7="Volumen", K25/SUM($K$12:$K$26)*$B$4, I25/SUM($I$12:$I$26)*$B$4)), 0) | M25: =IFERROR(I25/SUM($I$12:$I$26)*$B$5, 0) | N25: =I25+L25+M25 | O25: =IFERROR(N25/D25, 0) | P25: =N25*H25 | Q25: =IFERROR(I25/SUM($I$12:$I$26)*$B$6, 0) | R25: =N25+P25+Q25 | S25: =IFERROR(R25/D25, 0) | U25: =IFERROR(S25/(1-T25), 0) | V25: =U25*$B$9 | W25: =(U25-S25)*D25 | X25: =(N25+P25)*'1. Parametros y Tarifas'!$B$6 | Y25: =(N25+P25+X25)*$B$8
I26: =D26*E26 | J26: =D26*F26 | K26: =D26*G26 | L26: =IFERROR(IF($B$7="Peso", J26/SUM($J$12:$J$26)*$B$4, IF($B$7="Volumen", K26/SUM($K$12:$K$26)*$B$4, I26/SUM($I$12:$I$26)*$B$4)), 0) | M26: =IFERROR(I26/SUM($I$12:$I$26)*$B$5, 0) | N26: =I26+L26+M26 | O26: =IFERROR(N26/D26, 0) | P26: =N26*H26 | Q26: =IFERROR(I26/SUM($I$12:$I$26)*$B$6, 0) | R26: =N26+P26+Q26 | S26: =IFERROR(R26/D26, 0) | U26: =IFERROR(S26/(1-T26), 0) | V26: =U26*$B$9 | W26: =(U26-S26)*D26 | X26: =(N26+P26)*'1. Parametros y Tarifas'!$B$6 | Y26: =(N26+P26+X26)*$B$8
A27: TOTALES | D27: =SUM(D12:D26) | I27: =SUM(I12:I26) | J27: =SUM(J12:J26) | K27: =SUM(K12:K26) | L27: =SUM(L12:L26) | M27: =SUM(M12:M26) | N27: =SUM(N12:N26) | P27: =SUM(P12:P26) | Q27: =SUM(Q12:Q26) | R27: =SUM(R12:R26) | W27: =SUM(W12:W26) | X27: =SUM(X12:X26) | Y27: =SUM(Y12:Y26)
